MANIFEST.in
README.md
setup.py
FIXation.egg-info/PKG-INFO
FIXation.egg-info/SOURCES.txt
FIXation.egg-info/dependency_links.txt
FIXation.egg-info/entry_points.txt
FIXation.egg-info/top_level.txt
fixation/__init__.py
fixation/configuration.py
fixation/gen.py
fixation/jinja_filters.py
fixation/models.py
fixation/parse.py
fixation/templates/base_document.html
fixation/templates/base_fiximate.html
fixation/templates/document.html
fixation/templates/fields.html
fixation/templates/index.html
fixation/templates/index_components.html
fixation/templates/index_fields.html
fixation/templates/index_messages.html
fixation/templates/messages.html