Metadata-Version: 2.1
Name: FIXation
Version: 0.0.4
Summary: FIX repository tool
Home-page: https://gitlab.com/deepy/fixation
Author: Alex Nordlund
Author-email: deep.alexander@gmail.com
License: UNKNOWN
Platform: UNKNOWN
Classifier: Programming Language :: Python :: 3
Classifier: License :: OSI Approved :: MIT License
Classifier: Operating System :: OS Independent
